cloud_sheets_slim/__init__.py
cloud_sheets_slim/cloud_sheets_base.py
cloud_sheets_slim/google_sheets.py
cloud_sheets_slim/lark_sheets.py
cloud_sheets_slim/pandas_proxy.py
cloud_sheets_slim-0.3.0.dist-info/METADATA
cloud_sheets_slim-0.3.0.dist-info/WHEEL
cloud_sheets_slim-0.3.0.dist-info/RECORD
