Metadata-Version: 2.1
Name: cloud_sheets_slim
Version: 0.3.0
Summary: A lightweight cloud sheets operation library
Home-page: https://github.com/yingca1/cloud-sheets-slim
Author: Ying Cai
Author-email: i@caiying.me
Requires-Python: >=3.10,<4.0
Classifier: Programming Language :: Python :: 3
Classifier: Programming Language :: Python :: 3.10
Classifier: Programming Language :: Python :: 3.11
Classifier: Programming Language :: Python :: 3.12
Requires-Dist: gspread (>=5.12.0,<6.0.0)
Requires-Dist: lark-oapi (>=1.4.8,<2.0.0)
Requires-Dist: oauth2client (>=4.1.3,<5.0.0)
Requires-Dist: pandas (>=2.1.4,<3.0.0)
Requires-Dist: python-dotenv (>=1.0.0,<2.0.0)
